aws_toolset/__init__.py
aws_toolset/__main__.py
aws_toolset/aws_toolset.py
aws_toolset/modules/__init__.py
aws_toolset/modules/create_codestar_notifications.py
aws_toolset/modules/generate_ecs_execute_command.py
aws_toolset/modules/get_ec2_ecs_info.py
aws_toolset/modules/utils.py
aws_toolset-0.0.6.dist-info/LICENSE
aws_toolset-0.0.6.dist-info/METADATA
aws_toolset-0.0.6.dist-info/WHEEL
aws_toolset-0.0.6.dist-info/entry_points.txt
aws_toolset-0.0.6.dist-info/top_level.txt
aws_toolset-0.0.6.dist-info/RECORD
