Metadata-Version: 2.1
Name: aws-toolset
Version: 0.0.6
Summary: AWS Toolset for AWS Devs
Home-page: https://github.com/sgcooper78/aws_toolset
Author: Scott Cooper
Author-email: sgcooper78@gmail.com
Keywords: python,aws,boto3
Classifier: Programming Language :: Python :: 3
Classifier: License :: OSI Approved :: GNU Affero General Public License v3
Classifier: Operating System :: OS Independent
License-File: LICENSE
Requires-Dist: boto3
Requires-Dist: inquirer
